automlsa2/__init__.py
automlsa2/__main__.py
automlsa2/__version__.py
automlsa2/_exceptions.py
automlsa2/_settings.py
automlsa2/_versions.py
automlsa2/blast_functions.py
automlsa2/configuration.py
automlsa2/formatting.py
automlsa2/helper_functions.py
automlsa2/mafft.py
automlsa2/parse_args.py
automlsa2/pbar.py
automlsa2/phylogeny.py
automlsa2/tree_printer.py
automlsa2/validate_requirements.py
automlsa2-0.9.0.dist-info/LICENSE
automlsa2-0.9.0.dist-info/METADATA
automlsa2-0.9.0.dist-info/WHEEL
automlsa2-0.9.0.dist-info/entry_points.txt
automlsa2-0.9.0.dist-info/top_level.txt
automlsa2-0.9.0.dist-info/RECORD
