Metadata-Version: 2.1
Name: automlsa2
Version: 0.9.0
Summary: Automated Multi-Locus Sequence Analysis tool
Home-page: https://github.com/davised/automlsa2
Author: Edward Davis
Author-email: ed@cgrb.oregonstate.edu
Maintainer: Edward Davis
Maintainer-email: ed@cgrb.oregonstate.edu
License: Custom
Platform: UNKNOWN
Classifier: Development Status :: 4 - Beta
Classifier: Intended Audience :: Science/Research
Classifier: Natural Language :: English
Classifier: License :: Free for non-commercial use
Classifier: Operating System :: OS Independent
Classifier: Programming Language :: Python :: 3.7
Classifier: Programming Language :: Python :: 3.8
Classifier: Programming Language :: Python :: 3.9
Classifier: Programming Language :: Python :: Implementation :: PyPy
Classifier: Topic :: Scientific/Engineering :: Bio-Informatics
License-File: LICENSE
Requires-Dist: biopython
Requires-Dist: pandas (>=1.0.0)
Requires-Dist: numpy
Requires-Dist: rich
Requires-Dist: packaging
Requires-Dist: psutil
